boil/__init__.py
boil/__version__.py
boil/exceptions.py
boil/cli/__init__.py
boil/cli/commands.py
boil/common/__init__.py
boil/common/filters.py
boil/plate/__init__.py
boil/plate/manager.py
boil/plate/runner.py
boil/plates/__init__.py
boil/plates/__pycache__/__init__.cpython-310.pyc
boil/plates/ansible_role/README.md
boil/plates/ansible_role/__init__.py
boil/plates/ansible_role/__pycache__/__init__.cpython-310.pyc
boil/plates/ansible_role/templates/{{ role_name }}/README.md
boil/plates/ansible_role/templates/{{ role_name }}/defaults/main.yml
boil/plates/ansible_role/templates/{{ role_name }}/handlers/main.yml
boil/plates/ansible_role/templates/{{ role_name }}/meta/main.yml
boil/plates/ansible_role/templates/{{ role_name }}/tasks/main.yml
boil/plates/ansible_role/templates/{{ role_name }}/tests/inventory
boil/plates/ansible_role/templates/{{ role_name }}/tests/test.yml
boil/plates/ansible_role/templates/{{ role_name }}/vars/main.yml
boil/plates/bash_script/__init__.py
boil/plates/bash_script/__pycache__/__init__.cpython-310.pyc
boil/plates/bash_script/templates/{{ script_name }}.j2
boil/plates/flask-api/__init__.py
boil/plates/flask-api/templates/flask_api/.gitignore.j2
boil/plates/flask-api/templates/flask_api/Dockerfile.j2
boil/plates/flask-api/templates/flask_api/MANIFEST.in.j2
boil/plates/flask-api/templates/flask_api/Procfile.j2
boil/plates/flask-api/templates/flask_api/README.md.j2
boil/plates/flask-api/templates/flask_api/README.rst.j2
boil/plates/flask-api/templates/flask_api/requirements.txt.j2
boil/plates/flask-api/templates/flask_api/setup.py.j2
boil/plates/flask-api/templates/flask_api/test-requirements.txt.j2
boil/plates/flask-api/templates/flask_api/tox.ini.j2
boil/plates/flask-api/templates/flask_api/flask_api/__init__.py.j2
boil/plates/flask-api/templates/flask_api/flask_api/exceptions.py.j2
boil/plates/flask-api/templates/flask_api/flask_api/api/__init__.py.j2
boil/plates/flask-api/templates/flask_api/flask_api/api/app.py.j2
boil-0.3.1.dist-info/LICENSE.txt
boil-0.3.1.dist-info/METADATA
boil-0.3.1.dist-info/WHEEL
boil-0.3.1.dist-info/entry_points.txt
boil-0.3.1.dist-info/top_level.txt
boil-0.3.1.dist-info/RECORD
