Metadata-Version: 2.1
Name: boil
Version: 0.3.1
Summary: Radically simple app initialization
Home-page: https://github.com/bzurkowski/boil
Author: Bartosz Zurkowski
License: MIT
Classifier: Environment :: Console
Classifier: Intended Audience :: Developers
Classifier: Intended Audience :: Information Technology
Classifier: Intended Audience :: System Administrators
Classifier: License :: OSI Approved :: MIT License
Classifier: Natural Language :: English
Classifier: Operating System :: POSIX
Classifier: Programming Language :: Python :: 3.9
Classifier: Topic :: System :: Installation/Setup
Classifier: Topic :: System :: Systems Administration
Classifier: Topic :: Utilities
License-File: LICENSE.txt
Requires-Dist: Jinja2 (==3.1.2)
Requires-Dist: docopt (==0.6.2)
Requires-Dist: inflection (==0.5.1)
Requires-Dist: six (==1.16.0)
